phamt/phamt.c
phamt/__init__.py
phamt/c_core.cpython-37m-i386-linux-gnu.so
phamt/phamt.h
phamt/py_core.py
phamt/test/phamt.py
phamt/test/__init__.py
phamt-0.1.7.dist-info/top_level.txt
phamt-0.1.7.dist-info/LICENSE
phamt-0.1.7.dist-info/RECORD
phamt-0.1.7.dist-info/WHEEL
phamt-0.1.7.dist-info/METADATA
