Metadata-Version: 2.1
Name: phamt
Version: 0.1.7
Summary: A library implementing Persistent Hashed Array Mapped Tries in CPython
Home-page: https://github.com/noahbenson/phamt/
Download-URL: https://github.com/noahbenson/phamt/
Author: Noah C. Benson
Author-email: "Noah C. Benson" <nben@uw.edu>
License: MIT
Keywords: persistent immutable functional
Classifier: Development Status :: 4 - Beta
Classifier: Intended Audience :: Developers
Classifier: License :: OSI Approved :: MIT License
Classifier: Operating System :: Microsoft :: Windows
Classifier: Operating System :: POSIX
Classifier: Operating System :: Unix
Classifier: Operating System :: MacOS
Classifier: Programming Language :: C
Classifier: Programming Language :: Python :: Implementation :: CPython
Classifier: Programming Language :: Python :: 3
Classifier: Programming Language :: Python :: 3.7
Classifier: Programming Language :: Python :: 3.8
Classifier: Programming Language :: Python :: 3.9
Classifier: Programming Language :: Python :: 3.10
Classifier: Programming Language :: Python :: 3.11
Classifier: Topic :: Software Development
Classifier: Topic :: Software Development :: Libraries
Classifier: Topic :: Software Development :: Libraries :: Python Modules
Requires-Python: >=3.7
License-File: LICENSE
